wallet_connect/__init__.py
wallet_connect/frontend/build/asset-manifest.json
wallet_connect/frontend/build/bootstrap.min.css
wallet_connect/frontend/build/index.html
wallet_connect/frontend/build/precache-manifest.10cbbbcfa92f5f61a0f90ce5aca4fbf3.js
wallet_connect/frontend/build/precache-manifest.33678053181775643d1ce9dfe9627d02.js
wallet_connect/frontend/build/precache-manifest.462ad56492f72530684c2b80506ddb4d.js
wallet_connect/frontend/build/precache-manifest.53d1900e249f7be714a70bc92bd9992b.js
wallet_connect/frontend/build/precache-manifest.55ad964f6815f4466c8f416f216b5404.js
wallet_connect/frontend/build/precache-manifest.73d2020d0f1d70c83eeeb0d0d7e428dd.js
wallet_connect/frontend/build/precache-manifest.c188b6525835c7ef3042e6b505c0e78d.js
wallet_connect/frontend/build/precache-manifest.eb1eaae15a885c6d5292a906c0df967e.js
wallet_connect/frontend/build/service-worker.js
wallet_connect/frontend/build/static/js/2.24b52c9e.chunk.js
wallet_connect/frontend/build/static/js/2.24b52c9e.chunk.js.LICENSE.txt
wallet_connect/frontend/build/static/js/2.24b52c9e.chunk.js.map
wallet_connect/frontend/build/static/js/2.279307cf.chunk.js
wallet_connect/frontend/build/static/js/2.279307cf.chunk.js.LICENSE.txt
wallet_connect/frontend/build/static/js/2.279307cf.chunk.js.map
wallet_connect/frontend/build/static/js/2.58bc7d7a.chunk.js
wallet_connect/frontend/build/static/js/2.58bc7d7a.chunk.js.LICENSE.txt
wallet_connect/frontend/build/static/js/2.58bc7d7a.chunk.js.map
wallet_connect/frontend/build/static/js/2.d0d0ffc2.chunk.js
wallet_connect/frontend/build/static/js/2.d0d0ffc2.chunk.js.LICENSE.txt
wallet_connect/frontend/build/static/js/2.d0d0ffc2.chunk.js.map
wallet_connect/frontend/build/static/js/2.f95db60b.chunk.js
wallet_connect/frontend/build/static/js/2.f95db60b.chunk.js.LICENSE.txt
wallet_connect/frontend/build/static/js/2.f95db60b.chunk.js.map
wallet_connect/frontend/build/static/js/main.069cae75.chunk.js
streamlit_wallet_connect-0.1.0.dist-info/LICENSE
streamlit_wallet_connect-0.1.0.dist-info/METADATA
streamlit_wallet_connect-0.1.0.dist-info/WHEEL
streamlit_wallet_connect-0.1.0.dist-info/top_level.txt
streamlit_wallet_connect-0.1.0.dist-info/RECORD
