Metadata-Version: 2.1
Name: streamlit-wallet-connect
Version: 0.1.0
Summary: A Streamlit component for interacting with Web3.
Home-page: 
Author: AlgoveraAI
Author-email: hello@algovera.ai
Requires-Python: >=3.6
License-File: LICENSE
Requires-Dist: streamlit (>=0.63)
